cegaware/Enum.py
cegaware/Function.py
cegaware/Request.py
cegaware/Struct.py
cegaware/__init__.py
cegaware-0.1.11.dist-info/licenses/LICENCE
cegaware-0.1.11.dist-info/METADATA
cegaware-0.1.11.dist-info/WHEEL
cegaware-0.1.11.dist-info/top_level.txt
cegaware-0.1.11.dist-info/RECORD
