Metadata-Version: 2.4
Name: cegaware
Version: 0.1.11
Summary: Cegaware Python SDK
Author-email: Cegaware <contact@cegaware.com>
Project-URL: Homepage, https://www.cegaware.com
Classifier: Programming Language :: Python :: 3
Classifier: License :: Other/Proprietary License
Classifier: Operating System :: OS Independent
Requires-Python: >=3.8
License-File: LICENCE
Requires-Dist: requests
Requires-Dist: strenum
Dynamic: license-file
